uploadshapefile/__init__.py
uploadshapefile/functions.py
uploadshapefile/main.py
uploadshapefile-1.0.0.dist-info/METADATA
uploadshapefile-1.0.0.dist-info/WHEEL
uploadshapefile-1.0.0.dist-info/top_level.txt
uploadshapefile-1.0.0.dist-info/RECORD
